{
  "projects": [
    {
      "name": "Projeto Atualizado",
      "budget": "5500",
      "category": {
        "id": "1",
        "name": "Infra"
      },
      "cost": 800,
      "services": [
        {
          "name": "teste",
          "cost": "500",
          "description": "teste",
          "id": "652a2a0f-bf49-4f8e-b92a-b377e4d21d48"
        },
        {
          "name": "serviço 2",
          "cost": "300",
          "description": "serviço para contratar um designer",
          "id": "1119ffb3-8901-4c27-98e1-01afe0465039"
        }
      ],
      "id": 1
    },
    {
      "name": "Teste Mensagem",
      "budget": "10000",
      "category": {
        "id": "3",
        "name": "Design"
      },
      "cost": 500,
      "services": [
        {
          "name": "Primeiro serviço",
          "cost": "500",
          "description": "serviço para contratar um designer",
          "id": "cd61cd80-d299-4a3d-943c-0caa1ca8f541"
        }
      ],
      "id": 3
    },
    {
      "name": "Reserva de Armamento",
      "budget": "500",
      "category": {
        "id": "2",
        "name": "Desenvolvimento"
      },
      "cost": 0,
      "services": [],
      "id": 6
    },
    {
      "category": {
        "id": "1",
        "name": "Infra"
      },
      "name": "Lavanderia",
      "budget": "5000",
      "cost": 0,
      "services": [],
      "id": 7
    },
    {
      "name": "Design Cozinha Americana",
      "budget": "7000",
      "category": {
        "id": "3",
        "name": "Design"
      },
      "cost": 0,
      "services": [],
      "id": 8
    },
    {
      "name": "Cozinha",
      "budget": "11000",
      "category": {
        "id": "4",
        "name": "Planejamento"
      },
      "cost": 0,
      "services": [],
      "id": 9
    }
  ],
  "categories": [
    {
      "id": 1,
      "name": "Infra"
    },
    {
      "id": 2,
      "name": "Desenvolvimento"
    },
    {
      "id": 3,
      "name": "Design"
    },
    {
      "id": 4,
      "name": "Planejamento"
    },
    {
      "id": 5,
      "name": "Pessoal"
    }
  ]
}